{
  "meta": {
    "jobType": "seo",
    "jobTypeLabel": "SEO营销专家",
    "difficulty": "intermediate",
    "difficultyLabel": "中级",
    "title": "SEO优化师面试题库 - 中级篇",
    "version": "1.0.0",
    "description": "针对中级SEO优化师的100道面试题",
    "totalQuestions": 100,
    "categories": [
      "高级黑帽",
      "站群管理",
      "流量转化",
      "风险控制"
    ],
    "generatedAt": "2025-09-06T08:15:22.270Z"
  },
  "questions": [
    {
      "id": "seo_intermediate_高级黑帽_001",
      "originalId": 1,
      "category": "高级黑帽",
      "categoryKey": "高级黑帽",
      "type": "single",
      "question": "如何构建高效的蜘蛛池系统？",
      "options": [
        "多IP站群+泛解析+内容聚合",
        "单一服务器",
        "手动更新",
        "静态页面"
      ],
      "answer": "多IP站群+泛解析+内容聚合",
      "explanation": "蜘蛛池需要大量IP和域名资源"
    },
    {
      "id": "seo_intermediate_高级黑帽_002",
      "originalId": 2,
      "category": "高级黑帽",
      "categoryKey": "高级黑帽",
      "type": "multiple",
      "question": "站群系统的核心架构包括？（多选）",
      "options": [
        "主控系统",
        "节点管理",
        "内容分发",
        "监控系统"
      ],
      "answer": [
        "主控系统",
        "节点管理",
        "内容分发",
        "监控系统"
      ],
      "explanation": "完整的站群需要这些核心组件"
    },
    {
      "id": "seo_intermediate_高级黑帽_003",
      "originalId": 3,
      "category": "高级黑帽",
      "categoryKey": "高级黑帽",
      "type": "single",
      "question": "寄生虫程序最有效的传播方式是？",
      "options": [
        "利用CMS漏洞批量入侵",
        "手动上传",
        "FTP传输",
        "邮件发送"
      ],
      "answer": "利用CMS漏洞批量入侵",
      "explanation": "通过漏洞可以批量植入寄生虫"
    },
    {
      "id": "seo_intermediate_高级黑帽_004",
      "originalId": 4,
      "category": "高级黑帽",
      "categoryKey": "高级黑帽",
      "type": "single",
      "question": "如何规避搜索引擎的站群检测？",
      "options": [
        "IP分散、模板差异化、内容独特性",
        "使用相同模板",
        "集中IP段",
        "内容完全相同"
      ],
      "answer": "IP分散、模板差异化、内容独特性",
      "explanation": "差异化是规避检测的关键"
    },
    {
      "id": "seo_intermediate_高级黑帽_005",
      "originalId": 5,
      "category": "高级黑帽",
      "categoryKey": "高级黑帽",
      "type": "single",
      "question": "二级目录劫持的最佳实施方案是？",
      "options": [
        "获取高权重站点权限后建立隐藏目录",
        "直接购买",
        "申请合作",
        "公开建立"
      ],
      "answer": "获取高权重站点权限后建立隐藏目录",
      "explanation": "利用高权重站点的信任度"
    },
    {
      "id": "seo_intermediate_高级黑帽_006",
      "originalId": 6,
      "category": "高级黑帽",
      "categoryKey": "高级黑帽",
      "type": "multiple",
      "question": "泛目录程序的关键技术点包括？（多选）",
      "options": [
        "URL规则设计",
        "内容生成算法",
        "关键词布局",
        "蜘蛛识别"
      ],
      "answer": [
        "URL规则设计",
        "内容生成算法",
        "关键词布局",
        "蜘蛛识别"
      ],
      "explanation": "这些是泛目录的核心技术"
    },
    {
      "id": "seo_intermediate_高级黑帽_007",
      "originalId": 7,
      "category": "高级黑帽",
      "categoryKey": "高级黑帽",
      "type": "single",
      "question": "快速排名的核心算法原理是？",
      "options": [
        "模拟真实用户搜索点击行为",
        "大量外链",
        "内容优化",
        "网站改版"
      ],
      "answer": "模拟真实用户搜索点击行为",
      "explanation": "通过点击行为影响排名算法"
    },
    {
      "id": "seo_intermediate_高级黑帽_008",
      "originalId": 8,
      "category": "高级黑帽",
      "categoryKey": "高级黑帽",
      "type": "single",
      "question": "如何设计反向代理劫持系统？",
      "options": [
        "nginx配置+用户识别+内容替换",
        "直接跳转",
        "Frame嵌套",
        "JavaScript跳转"
      ],
      "answer": "nginx配置+用户识别+内容替换",
      "explanation": "反向代理可以无缝劫持流量"
    },
    {
      "id": "seo_intermediate_高级黑帽_009",
      "originalId": 9,
      "category": "高级黑帽",
      "categoryKey": "高级黑帽",
      "type": "single",
      "question": "黑帽SEO中的\"养站\"策略是指？",
      "options": [
        "先正常运营积累权重再做黑帽",
        "直接上黑帽",
        "购买老域名",
        "批量建站"
      ],
      "answer": "先正常运营积累权重再做黑帽",
      "explanation": "养站可以获得更高的初始信任度"
    },
    {
      "id": "seo_intermediate_高级黑帽_010",
      "originalId": 10,
      "category": "高级黑帽",
      "categoryKey": "高级黑帽",
      "type": "multiple",
      "question": "链轮系统的构建要素包括？（多选）",
      "options": [
        "节点站规划",
        "链接策略",
        "权重传递路径",
        "风险隔离"
      ],
      "answer": [
        "节点站规划",
        "链接策略",
        "权重传递路径",
        "风险隔离"
      ],
      "explanation": "链轮需要精心设计避免被识别"
    },
    {
      "id": "seo_intermediate_高级黑帽_011",
      "originalId": 11,
      "category": "高级黑帽",
      "categoryKey": "高级黑帽",
      "type": "single",
      "question": "如何实现搜索引擎劫持不被发现？",
      "options": [
        "UserAgent识别+IP段判断+时间控制",
        "所有访客劫持",
        "只劫持爬虫",
        "随机劫持"
      ],
      "answer": "UserAgent识别+IP段判断+时间控制",
      "explanation": "精准识别避免暴露"
    },
    {
      "id": "seo_intermediate_高级黑帽_012",
      "originalId": 12,
      "category": "高级黑帽",
      "categoryKey": "高级黑帽",
      "type": "single",
      "question": "站群内容生成的最优方案是？",
      "options": [
        "AI改写+段落重组+同义词替换",
        "完全复制",
        "人工撰写",
        "机器翻译"
      ],
      "answer": "AI改写+段落重组+同义词替换",
      "explanation": "保证内容独特性避免被识别"
    },
    {
      "id": "seo_intermediate_高级黑帽_013",
      "originalId": 13,
      "category": "高级黑帽",
      "categoryKey": "高级黑帽",
      "type": "single",
      "question": "如何构建私有PBN网络？",
      "options": [
        "收购过期域名+独立IP+差异化内容",
        "新域名批量注册",
        "相同IP建站",
        "模板统一"
      ],
      "answer": "收购过期域名+独立IP+差异化内容",
      "explanation": "PBN需要看起来像真实独立网站"
    },
    {
      "id": "seo_intermediate_高级黑帽_014",
      "originalId": 14,
      "category": "高级黑帽",
      "categoryKey": "高级黑帽",
      "type": "multiple",
      "question": "黑帽SEO的风控措施包括？（多选）",
      "options": [
        "站点隔离",
        "域名备份",
        "流量监控",
        "收益分散"
      ],
      "answer": [
        "站点隔离",
        "域名备份",
        "流量监控",
        "收益分散"
      ],
      "explanation": "风控是黑帽SEO的生存之道"
    },
    {
      "id": "seo_intermediate_高级黑帽_015",
      "originalId": 15,
      "category": "高级黑帽",
      "categoryKey": "高级黑帽",
      "type": "single",
      "question": "如何绕过Google的垃圾链接检测？",
      "options": [
        "链接速度控制+来源多样化+锚文本自然",
        "大量群发",
        "购买链接包",
        "交换链接"
      ],
      "answer": "链接速度控制+来源多样化+锚文本自然",
      "explanation": "模拟自然链接增长模式"
    },
    {
      "id": "seo_intermediate_高级黑帽_016",
      "originalId": 16,
      "category": "高级黑帽",
      "categoryKey": "高级黑帽",
      "type": "single",
      "question": "301跳转劫持的最佳时机是？",
      "options": [
        "网站获得排名稳定后",
        "刚建站时",
        "被K之后",
        "没有流量时"
      ],
      "answer": "网站获得排名稳定后",
      "explanation": "有排名后劫持价值最大"
    },
    {
      "id": "seo_intermediate_高级黑帽_017",
      "originalId": 17,
      "category": "高级黑帽",
      "categoryKey": "高级黑帽",
      "type": "single",
      "question": "如何利用schema标记做黑帽？",
      "options": [
        "虚假评分和评论标记",
        "正常使用",
        "不使用schema",
        "只标记真实信息"
      ],
      "answer": "虚假评分和评论标记",
      "explanation": "滥用结构化数据获取富片段"
    },
    {
      "id": "seo_intermediate_高级黑帽_018",
      "originalId": 18,
      "category": "高级黑帽",
      "categoryKey": "高级黑帽",
      "type": "multiple",
      "question": "蜘蛛池的维护工作包括？（多选）",
      "options": [
        "域名续费",
        "内容更新",
        "死链清理",
        "收录监控"
      ],
      "answer": [
        "域名续费",
        "内容更新",
        "死链清理",
        "收录监控"
      ],
      "explanation": "蜘蛛池需要持续维护"
    },
    {
      "id": "seo_intermediate_高级黑帽_019",
      "originalId": 19,
      "category": "高级黑帽",
      "categoryKey": "高级黑帽",
      "type": "single",
      "question": "如何判断域名是否被惩罚过？",
      "options": [
        "site命令+历史快照+外链分析",
        "只看PR值",
        "查看年龄",
        "随机判断"
      ],
      "answer": "site命令+历史快照+外链分析",
      "explanation": "多维度检查域名历史"
    },
    {
      "id": "seo_intermediate_高级黑帽_020",
      "originalId": 20,
      "category": "高级黑帽",
      "categoryKey": "高级黑帽",
      "type": "single",
      "question": "镜像站群的IP配置策略是？",
      "options": [
        "不同C段分散+CDN混淆",
        "同一C段",
        "相邻IP",
        "随机分配"
      ],
      "answer": "不同C段分散+CDN混淆",
      "explanation": "IP分散降低关联风险"
    },
    {
      "id": "seo_intermediate_高级黑帽_021",
      "originalId": 21,
      "category": "高级黑帽",
      "categoryKey": "高级黑帽",
      "type": "single",
      "question": "如何利用社交信号做黑帽SEO？",
      "options": [
        "批量创建社交账号推广",
        "真实运营",
        "不使用社交",
        "购买粉丝"
      ],
      "answer": "批量创建社交账号推广",
      "explanation": "社交信号可以影响排名"
    },
    {
      "id": "seo_intermediate_高级黑帽_022",
      "originalId": 22,
      "category": "高级黑帽",
      "categoryKey": "高级黑帽",
      "type": "multiple",
      "question": "内容采集的高级技巧包括？（多选）",
      "options": [
        "反爬虫绕过",
        "多源聚合",
        "智能去重",
        "格式转换"
      ],
      "answer": [
        "反爬虫绕过",
        "多源聚合",
        "智能去重",
        "格式转换"
      ],
      "explanation": "高级采集需要技术手段"
    },
    {
      "id": "seo_intermediate_高级黑帽_023",
      "originalId": 23,
      "category": "高级黑帽",
      "categoryKey": "高级黑帽",
      "type": "single",
      "question": "如何构建金字塔链接结构？",
      "options": [
        "底层大量低质链接逐层传递",
        "所有直接指向",
        "随机链接",
        "不建立结构"
      ],
      "answer": "底层大量低质链接逐层传递",
      "explanation": "金字塔结构过滤和传递权重"
    },
    {
      "id": "seo_intermediate_高级黑帽_024",
      "originalId": 24,
      "category": "高级黑帽",
      "categoryKey": "高级黑帽",
      "type": "single",
      "question": "黑帽SEO项目的ROI如何计算？",
      "options": [
        "(收益-成本)/成本×100%",
        "只看收益",
        "只看成本",
        "不计算"
      ],
      "answer": "(收益-成本)/成本×100%",
      "explanation": "ROI是评估项目价值的关键"
    },
    {
      "id": "seo_intermediate_高级黑帽_025",
      "originalId": 25,
      "category": "高级黑帽",
      "categoryKey": "高级黑帽",
      "type": "single",
      "question": "如何应对算法更新对黑帽的打击？",
      "options": [
        "多样化策略+快速调整+风险分散",
        "继续原策略",
        "完全停止",
        "等待恢复"
      ],
      "answer": "多样化策略+快速调整+风险分散",
      "explanation": "灵活应对是生存关键"
    },
    {
      "id": "seo_intermediate_站群管理_026",
      "originalId": 26,
      "category": "站群管理",
      "categoryKey": "站群管理",
      "type": "single",
      "question": "站群CMS选择的首要考虑因素是？",
      "options": [
        "批量管理能力和API支持",
        "界面美观",
        "价格便宜",
        "功能简单"
      ],
      "answer": "批量管理能力和API支持",
      "explanation": "效率是站群管理的核心"
    },
    {
      "id": "seo_intermediate_站群管理_027",
      "originalId": 27,
      "category": "站群管理",
      "categoryKey": "站群管理",
      "type": "multiple",
      "question": "站群域名管理策略包括？（多选）",
      "options": [
        "批量注册",
        "分散注册商",
        "隐私保护",
        "自动续费"
      ],
      "answer": [
        "批量注册",
        "分散注册商",
        "隐私保护",
        "自动续费"
      ],
      "explanation": "域名管理需要规避风险"
    },
    {
      "id": "seo_intermediate_站群管理_028",
      "originalId": 28,
      "category": "站群管理",
      "categoryKey": "站群管理",
      "type": "single",
      "question": "如何实现站群内容自动发布？",
      "options": [
        "API接口+定时任务+内容队列",
        "手动发布",
        "批量导入",
        "复制粘贴"
      ],
      "answer": "API接口+定时任务+内容队列",
      "explanation": "自动化是规模化的基础"
    },
    {
      "id": "seo_intermediate_站群管理_029",
      "originalId": 29,
      "category": "站群管理",
      "categoryKey": "站群管理",
      "type": "single",
      "question": "站群服务器的最佳配置是？",
      "options": [
        "多IP服务器+负载均衡+CDN",
        "单一服务器",
        "虚拟主机",
        "免费空间"
      ],
      "answer": "多IP服务器+负载均衡+CDN",
      "explanation": "服务器配置影响站群稳定性"
    },
    {
      "id": "seo_intermediate_站群管理_030",
      "originalId": 30,
      "category": "站群管理",
      "categoryKey": "站群管理",
      "type": "single",
      "question": "如何监控站群的整体健康状态？",
      "options": [
        "集中监控系统+异常报警+数据分析",
        "手动检查",
        "不监控",
        "用户反馈"
      ],
      "answer": "集中监控系统+异常报警+数据分析",
      "explanation": "监控帮助及时发现问题"
    },
    {
      "id": "seo_intermediate_站群管理_031",
      "originalId": 31,
      "category": "站群管理",
      "categoryKey": "站群管理",
      "type": "multiple",
      "question": "火车头采集器的高级功能包括？（多选）",
      "options": [
        "JavaScript渲染",
        "验证码识别",
        "代理池管理",
        "数据清洗"
      ],
      "answer": [
        "JavaScript渲染",
        "验证码识别",
        "代理池管理",
        "数据清洗"
      ],
      "explanation": "掌握高级功能提高采集效率"
    },
    {
      "id": "seo_intermediate_站群管理_032",
      "originalId": 32,
      "category": "站群管理",
      "categoryKey": "站群管理",
      "type": "single",
      "question": "站群数据库设计的原则是？",
      "options": [
        "分库分表+读写分离+缓存优化",
        "单一数据库",
        "文件存储",
        "内存数据库"
      ],
      "answer": "分库分表+读写分离+缓存优化",
      "explanation": "数据库设计影响站群性能"
    },
    {
      "id": "seo_intermediate_站群管理_033",
      "originalId": 33,
      "category": "站群管理",
      "categoryKey": "站群管理",
      "type": "single",
      "question": "如何实现站群的负载均衡？",
      "options": [
        "Nginx反向代理+DNS轮询",
        "单点访问",
        "随机分配",
        "固定分配"
      ],
      "answer": "Nginx反向代理+DNS轮询",
      "explanation": "负载均衡提高可用性"
    },
    {
      "id": "seo_intermediate_站群管理_034",
      "originalId": 34,
      "category": "站群管理",
      "categoryKey": "站群管理",
      "type": "single",
      "question": "站群备份策略应该是？",
      "options": [
        "增量备份+异地存储+定期恢复测试",
        "不备份",
        "本地备份",
        "偶尔备份"
      ],
      "answer": "增量备份+异地存储+定期恢复测试",
      "explanation": "完善的备份策略防止数据丢失"
    },
    {
      "id": "seo_intermediate_站群管理_035",
      "originalId": 35,
      "category": "站群管理",
      "categoryKey": "站群管理",
      "type": "single",
      "question": "如何优化站群的爬虫抓取效率？",
      "options": [
        "XML地图+robots优化+内链结构",
        "限制爬虫",
        "不优化",
        "随机处理"
      ],
      "answer": "XML地图+robots优化+内链结构",
      "explanation": "优化爬虫效率提高收录"
    },
    {
      "id": "seo_intermediate_站群管理_036",
      "originalId": 36,
      "category": "站群管理",
      "categoryKey": "站群管理",
      "type": "multiple",
      "question": "站群安全防护措施包括？（多选）",
      "options": [
        "WAF防火墙",
        "DDoS防护",
        "代码审计",
        "权限管理"
      ],
      "answer": [
        "WAF防火墙",
        "DDoS防护",
        "代码审计",
        "权限管理"
      ],
      "explanation": "安全是站群稳定运行的保障"
    },
    {
      "id": "seo_intermediate_站群管理_037",
      "originalId": 37,
      "category": "站群管理",
      "categoryKey": "站群管理",
      "type": "single",
      "question": "如何实现站群的模板差异化？",
      "options": [
        "模板变量+随机组合+CSS差异",
        "使用同一模板",
        "手动修改",
        "不使用模板"
      ],
      "answer": "模板变量+随机组合+CSS差异",
      "explanation": "模板差异化避免被识别为站群"
    },
    {
      "id": "seo_intermediate_站群管理_038",
      "originalId": 38,
      "category": "站群管理",
      "categoryKey": "站群管理",
      "type": "single",
      "question": "站群内容更新的最佳频率是？",
      "options": [
        "根据站点权重分级更新",
        "每天更新",
        "从不更新",
        "随机更新"
      ],
      "answer": "根据站点权重分级更新",
      "explanation": "分级管理提高效率"
    },
    {
      "id": "seo_intermediate_站群管理_039",
      "originalId": 39,
      "category": "站群管理",
      "categoryKey": "站群管理",
      "type": "single",
      "question": "如何处理站群中的死链？",
      "options": [
        "自动检测+301重定向+404优化",
        "不处理",
        "删除站点",
        "手动修复"
      ],
      "answer": "自动检测+301重定向+404优化",
      "explanation": "死链处理影响站群质量"
    },
    {
      "id": "seo_intermediate_站群管理_040",
      "originalId": 40,
      "category": "站群管理",
      "categoryKey": "站群管理",
      "type": "multiple",
      "question": "站群流量变现方式包括？（多选）",
      "options": [
        "广告联盟",
        "CPA推广",
        "导流销售",
        "会员服务"
      ],
      "answer": [
        "广告联盟",
        "CPA推广",
        "导流销售",
        "会员服务"
      ],
      "explanation": "多元化变现提高收益"
    },
    {
      "id": "seo_intermediate_站群管理_041",
      "originalId": 41,
      "category": "站群管理",
      "categoryKey": "站群管理",
      "type": "single",
      "question": "如何避免站群之间的关联？",
      "options": [
        "WHOIS隐私+不同主机+差异内容",
        "相互链接",
        "相同信息",
        "集中管理"
      ],
      "answer": "WHOIS隐私+不同主机+差异内容",
      "explanation": "避免关联是站群生存的关键"
    },
    {
      "id": "seo_intermediate_站群管理_042",
      "originalId": 42,
      "category": "站群管理",
      "categoryKey": "站群管理",
      "type": "single",
      "question": "站群日志分析的重点是？",
      "options": [
        "爬虫行为+异常流量+收录情况",
        "访客数量",
        "页面浏览",
        "停留时间"
      ],
      "answer": "爬虫行为+异常流量+收录情况",
      "explanation": "日志分析帮助优化策略"
    },
    {
      "id": "seo_intermediate_站群管理_043",
      "originalId": 43,
      "category": "站群管理",
      "categoryKey": "站群管理",
      "type": "single",
      "question": "如何批量处理站群的SSL证书？",
      "options": [
        "Let's Encrypt自动化+通配符证书",
        "不使用SSL",
        "手动申请",
        "购买昂贵证书"
      ],
      "answer": "Let's Encrypt自动化+通配符证书",
      "explanation": "SSL对排名有积极影响"
    },
    {
      "id": "seo_intermediate_站群管理_044",
      "originalId": 44,
      "category": "站群管理",
      "categoryKey": "站群管理",
      "type": "multiple",
      "question": "站群成本控制的要点包括？（多选）",
      "options": [
        "域名批量采购",
        "服务器优化",
        "自动化运维",
        "内容成本控制"
      ],
      "answer": [
        "域名批量采购",
        "服务器优化",
        "自动化运维",
        "内容成本控制"
      ],
      "explanation": "成本控制影响ROI"
    },
    {
      "id": "seo_intermediate_站群管理_045",
      "originalId": 45,
      "category": "站群管理",
      "categoryKey": "站群管理",
      "type": "single",
      "question": "如何评估站群项目的成功？",
      "options": [
        "ROI+流量增长+收录率+稳定性",
        "只看流量",
        "只看收益",
        "主观判断"
      ],
      "answer": "ROI+流量增长+收录率+稳定性",
      "explanation": "综合指标评估项目成功"
    },
    {
      "id": "seo_intermediate_站群管理_046",
      "originalId": 46,
      "category": "站群管理",
      "categoryKey": "站群管理",
      "type": "single",
      "question": "站群被K的恢复策略是？",
      "options": [
        "分析原因+清理问题+申诉+重建",
        "放弃域名",
        "继续黑帽",
        "等待自动恢复"
      ],
      "answer": "分析原因+清理问题+申诉+重建",
      "explanation": "正确的恢复策略可能挽回损失"
    },
    {
      "id": "seo_intermediate_站群管理_047",
      "originalId": 47,
      "category": "站群管理",
      "categoryKey": "站群管理",
      "type": "single",
      "question": "如何设计站群的内链策略？",
      "options": [
        "主站引导+相关性链接+权重传递",
        "随机链接",
        "全部互链",
        "不做内链"
      ],
      "answer": "主站引导+相关性链接+权重传递",
      "explanation": "内链策略影响权重分配"
    },
    {
      "id": "seo_intermediate_站群管理_048",
      "originalId": 48,
      "category": "站群管理",
      "categoryKey": "站群管理",
      "type": "multiple",
      "question": "站群自动化工具包括？（多选）",
      "options": [
        "Selenium",
        "Puppeteer",
        "Python脚本",
        "Shell脚本"
      ],
      "answer": [
        "Selenium",
        "Puppeteer",
        "Python脚本",
        "Shell脚本"
      ],
      "explanation": "自动化工具提高管理效率"
    },
    {
      "id": "seo_intermediate_站群管理_049",
      "originalId": 49,
      "category": "站群管理",
      "categoryKey": "站群管理",
      "type": "single",
      "question": "站群项目的生命周期管理包括？",
      "options": [
        "规划-实施-监控-优化-退出",
        "永久运营",
        "短期运作",
        "不管理"
      ],
      "answer": "规划-实施-监控-优化-退出",
      "explanation": "生命周期管理确保项目价值最大化"
    },
    {
      "id": "seo_intermediate_站群管理_050",
      "originalId": 50,
      "category": "站群管理",
      "categoryKey": "站群管理",
      "type": "single",
      "question": "如何处理站群的版权问题？",
      "options": [
        "内容改写+图片替换+免责声明",
        "直接复制",
        "不考虑版权",
        "购买版权"
      ],
      "answer": "内容改写+图片替换+免责声明",
      "explanation": "规避版权风险避免法律问题"
    },
    {
      "id": "seo_intermediate_流量转化_051",
      "originalId": 51,
      "category": "流量转化",
      "categoryKey": "流量转化",
      "type": "single",
      "question": "如何提高黑帽SEO的转化率？",
      "options": [
        "着陆页优化+用户体验+A/B测试",
        "只追求流量",
        "不关注转化",
        "随机优化"
      ],
      "answer": "着陆页优化+用户体验+A/B测试",
      "explanation": "转化率决定最终收益"
    },
    {
      "id": "seo_intermediate_流量转化_052",
      "originalId": 52,
      "category": "流量转化",
      "categoryKey": "流量转化",
      "type": "multiple",
      "question": "流量劫持的主要方式包括？（多选）",
      "options": [
        "DNS劫持",
        "HTTP劫持",
        "搜索劫持",
        "点击劫持"
      ],
      "answer": [
        "DNS劫持",
        "HTTP劫持",
        "搜索劫持",
        "点击劫持"
      ],
      "explanation": "不同劫持方式有不同应用场景"
    },
    {
      "id": "seo_intermediate_流量转化_053",
      "originalId": 53,
      "category": "流量转化",
      "categoryKey": "流量转化",
      "type": "single",
      "question": "如何识别和过滤无效流量？",
      "options": [
        "IP分析+行为识别+设备指纹",
        "不过滤",
        "全部接受",
        "随机过滤"
      ],
      "answer": "IP分析+行为识别+设备指纹",
      "explanation": "过滤无效流量提高质量"
    },
    {
      "id": "seo_intermediate_流量转化_054",
      "originalId": 54,
      "category": "流量转化",
      "categoryKey": "流量转化",
      "type": "single",
      "question": "CPA推广中如何防止扣量？",
      "options": [
        "多渠道验证+数据对比+第三方监控",
        "相信联盟",
        "不监控",
        "手动统计"
      ],
      "answer": "多渠道验证+数据对比+第三方监控",
      "explanation": "防扣量保护收益"
    },
    {
      "id": "seo_intermediate_流量转化_055",
      "originalId": 55,
      "category": "流量转化",
      "categoryKey": "流量转化",
      "type": "single",
      "question": "如何优化跳转链的转化？",
      "options": [
        "减少跳转次数+加速跳转+优化体验",
        "多次跳转",
        "直接跳转",
        "不优化"
      ],
      "answer": "减少跳转次数+加速跳转+优化体验",
      "explanation": "跳转优化减少流失"
    },
    {
      "id": "seo_intermediate_流量转化_056",
      "originalId": 56,
      "category": "流量转化",
      "categoryKey": "流量转化",
      "type": "multiple",
      "question": "提高广告点击率的方法包括？（多选）",
      "options": [
        "位置优化",
        "样式测试",
        "内容相关",
        "加载速度"
      ],
      "answer": [
        "位置优化",
        "样式测试",
        "内容相关",
        "加载速度"
      ],
      "explanation": "多维度优化提高CTR"
    },
    {
      "id": "seo_intermediate_流量转化_057",
      "originalId": 57,
      "category": "流量转化",
      "categoryKey": "流量转化",
      "type": "single",
      "question": "如何选择合适的广告联盟？",
      "options": [
        "信誉度+单价+结算周期+扣量情况",
        "只看单价",
        "随便选择",
        "选最大的"
      ],
      "answer": "信誉度+单价+结算周期+扣量情况",
      "explanation": "综合评估选择联盟"
    },
    {
      "id": "seo_intermediate_流量转化_058",
      "originalId": 58,
      "category": "流量转化",
      "categoryKey": "流量转化",
      "type": "single",
      "question": "移动端流量劫持的特点是？",
      "options": [
        "APP劫持+运营商劫持+WiFi劫持",
        "与PC相同",
        "更简单",
        "不能劫持"
      ],
      "answer": "APP劫持+运营商劫持+WiFi劫持",
      "explanation": "移动端有特殊的劫持方式"
    },
    {
      "id": "seo_intermediate_流量转化_059",
      "originalId": 59,
      "category": "流量转化",
      "categoryKey": "流量转化",
      "type": "single",
      "question": "如何提高站群的用户停留时间？",
      "options": [
        "内容质量+内链优化+交互设计",
        "弹窗阻止",
        "隐藏关闭",
        "强制停留"
      ],
      "answer": "内容质量+内链优化+交互设计",
      "explanation": "自然的用户行为更有价值"
    },
    {
      "id": "seo_intermediate_流量转化_060",
      "originalId": 60,
      "category": "流量转化",
      "categoryKey": "流量转化",
      "type": "multiple",
      "question": "流量变现的KPI指标包括？（多选）",
      "options": [
        "RPM",
        "CTR",
        "CVR",
        "ROI"
      ],
      "answer": [
        "RPM",
        "CTR",
        "CVR",
        "ROI"
      ],
      "explanation": "KPI指标指导优化方向"
    },
    {
      "id": "seo_intermediate_流量转化_061",
      "originalId": 61,
      "category": "流量转化",
      "categoryKey": "流量转化",
      "type": "single",
      "question": "如何处理恶意点击？",
      "options": [
        "IP封禁+行为分析+验证机制",
        "不处理",
        "全部计费",
        "手动排查"
      ],
      "answer": "IP封禁+行为分析+验证机制",
      "explanation": "防恶意点击保护广告收益"
    },
    {
      "id": "seo_intermediate_流量转化_062",
      "originalId": 62,
      "category": "流量转化",
      "categoryKey": "流量转化",
      "type": "single",
      "question": "桥页的转化优化重点是？",
      "options": [
        "关键词匹配+快速跳转+相关性",
        "内容丰富",
        "停留时间",
        "用户交互"
      ],
      "answer": "关键词匹配+快速跳转+相关性",
      "explanation": "桥页的目的是引导转化"
    },
    {
      "id": "seo_intermediate_流量转化_063",
      "originalId": 63,
      "category": "流量转化",
      "categoryKey": "流量转化",
      "type": "single",
      "question": "如何分析流量来源质量？",
      "options": [
        "跳出率+停留时间+转化率+回访率",
        "只看数量",
        "不分析",
        "主观判断"
      ],
      "answer": "跳出率+停留时间+转化率+回访率",
      "explanation": "质量分析优化流量策略"
    },
    {
      "id": "seo_intermediate_流量转化_064",
      "originalId": 64,
      "category": "流量转化",
      "categoryKey": "流量转化",
      "type": "multiple",
      "question": "影响广告收益的因素包括？（多选）",
      "options": [
        "流量质量",
        "广告位置",
        "行业类别",
        "地域分布"
      ],
      "answer": [
        "流量质量",
        "广告位置",
        "行业类别",
        "地域分布"
      ],
      "explanation": "多因素影响广告收益"
    },
    {
      "id": "seo_intermediate_流量转化_065",
      "originalId": 65,
      "category": "流量转化",
      "categoryKey": "流量转化",
      "type": "single",
      "question": "如何优化移动端的转化率？",
      "options": [
        "响应式设计+加载速度+简化流程",
        "PC端相同",
        "不优化移动",
        "强制APP"
      ],
      "answer": "响应式设计+加载速度+简化流程",
      "explanation": "移动端需要特别优化"
    },
    {
      "id": "seo_intermediate_流量转化_066",
      "originalId": 66,
      "category": "流量转化",
      "categoryKey": "流量转化",
      "type": "single",
      "question": "弹窗广告的最佳展示时机是？",
      "options": [
        "用户停留一定时间后",
        "立即弹出",
        "离开时弹出",
        "随机弹出"
      ],
      "answer": "用户停留一定时间后",
      "explanation": "时机选择影响用户体验和转化"
    },
    {
      "id": "seo_intermediate_流量转化_067",
      "originalId": 67,
      "category": "流量转化",
      "categoryKey": "流量转化",
      "type": "single",
      "question": "如何提高联盟推广的EPC？",
      "options": [
        "选品优化+流量筛选+着陆页优化",
        "增加流量",
        "降低成本",
        "不优化"
      ],
      "answer": "选品优化+流量筛选+着陆页优化",
      "explanation": "EPC是衡量推广效果的关键"
    },
    {
      "id": "seo_intermediate_流量转化_068",
      "originalId": 68,
      "category": "流量转化",
      "categoryKey": "流量转化",
      "type": "multiple",
      "question": "流量套利的风险包括？（多选）",
      "options": [
        "账号封禁",
        "流量质量",
        "政策变化",
        "竞争加剧"
      ],
      "answer": [
        "账号封禁",
        "流量质量",
        "政策变化",
        "竞争加剧"
      ],
      "explanation": "了解风险才能规避风险"
    },
    {
      "id": "seo_intermediate_流量转化_069",
      "originalId": 69,
      "category": "流量转化",
      "categoryKey": "流量转化",
      "type": "single",
      "question": "如何设计高转化的钓鱼页面？",
      "options": [
        "不建议从事违法活动",
        "模仿官网",
        "诱导点击",
        "虚假承诺"
      ],
      "answer": "不建议从事违法活动",
      "explanation": "钓鱼页面属于违法行为"
    },
    {
      "id": "seo_intermediate_流量转化_070",
      "originalId": 70,
      "category": "流量转化",
      "categoryKey": "流量转化",
      "type": "single",
      "question": "直链和跳转链的选择依据是？",
      "options": [
        "根据平台规则和转化需求",
        "always直链",
        "always跳转",
        "随机选择"
      ],
      "answer": "根据平台规则和转化需求",
      "explanation": "不同场景选择不同方式"
    },
    {
      "id": "seo_intermediate_流量转化_071",
      "originalId": 71,
      "category": "流量转化",
      "categoryKey": "流量转化",
      "type": "single",
      "question": "如何优化Google AdSense收益？",
      "options": [
        "广告位置+尺寸优化+内容相关性",
        "增加广告数量",
        "点击作弊",
        "购买流量"
      ],
      "answer": "广告位置+尺寸优化+内容相关性",
      "explanation": "合规优化提高长期收益"
    },
    {
      "id": "seo_intermediate_流量转化_072",
      "originalId": 72,
      "category": "流量转化",
      "categoryKey": "流量转化",
      "type": "multiple",
      "question": "影响转化率的页面因素包括？（多选）",
      "options": [
        "加载速度",
        "视觉设计",
        "文案内容",
        "信任标识"
      ],
      "answer": [
        "加载速度",
        "视觉设计",
        "文案内容",
        "信任标识"
      ],
      "explanation": "页面优化是转化的基础"
    },
    {
      "id": "seo_intermediate_流量转化_073",
      "originalId": 73,
      "category": "流量转化",
      "categoryKey": "流量转化",
      "type": "single",
      "question": "如何防止广告屏蔽插件？",
      "options": [
        "反屏蔽脚本+原生广告+付费墙",
        "强制关闭",
        "不处理",
        "禁止访问"
      ],
      "answer": "反屏蔽脚本+原生广告+付费墙",
      "explanation": "多种策略应对广告屏蔽"
    },
    {
      "id": "seo_intermediate_流量转化_074",
      "originalId": 74,
      "category": "流量转化",
      "categoryKey": "流量转化",
      "type": "single",
      "question": "社交媒体流量的转化特点是？",
      "options": [
        "信任度高但直接转化低",
        "转化率最高",
        "质量最差",
        "无法转化"
      ],
      "answer": "信任度高但直接转化低",
      "explanation": "社交流量需要培养转化"
    },
    {
      "id": "seo_intermediate_流量转化_075",
      "originalId": 75,
      "category": "流量转化",
      "categoryKey": "流量转化",
      "type": "single",
      "question": "如何计算流量的真实价值？",
      "options": [
        "LTV-CAC分析",
        "只看当前收益",
        "不计算",
        "估算"
      ],
      "answer": "LTV-CAC分析",
      "explanation": "生命周期价值评估更准确"
    },
    {
      "id": "seo_intermediate_风险控制_076",
      "originalId": 76,
      "category": "风险控制",
      "categoryKey": "风险控制",
      "type": "single",
      "question": "如何识别搜索引擎的算法更新？",
      "options": [
        "排名波动+官方公告+行业动态",
        "不关注",
        "等待通知",
        "猜测"
      ],
      "answer": "排名波动+官方公告+行业动态",
      "explanation": "及时发现算法更新调整策略"
    },
    {
      "id": "seo_intermediate_风险控制_077",
      "originalId": 77,
      "category": "风险控制",
      "categoryKey": "风险控制",
      "type": "multiple",
      "question": "黑帽SEO的法律风险包括？（多选）",
      "options": [
        "侵犯版权",
        "不正当竞争",
        "网络攻击",
        "数据泄露"
      ],
      "answer": [
        "侵犯版权",
        "不正当竞争",
        "网络攻击",
        "数据泄露"
      ],
      "explanation": "了解法律风险避免违法"
    },
    {
      "id": "seo_intermediate_风险控制_078",
      "originalId": 78,
      "category": "风险控制",
      "categoryKey": "风险控制",
      "type": "single",
      "question": "如何应对竞争对手的负面SEO攻击？",
      "options": [
        "监控外链+拒绝工具+证据收集",
        "反击攻击",
        "不处理",
        "放弃网站"
      ],
      "answer": "监控外链+拒绝工具+证据收集",
      "explanation": "正确应对保护网站"
    },
    {
      "id": "seo_intermediate_风险控制_079",
      "originalId": 79,
      "category": "风险控制",
      "categoryKey": "风险控制",
      "type": "single",
      "question": "站群项目的退出策略应该包括？",
      "options": [
        "域名处理+数据备份+流量转移",
        "直接关闭",
        "不退出",
        "卖给他人"
      ],
      "answer": "域名处理+数据备份+流量转移",
      "explanation": "合理退出最大化剩余价值"
    },
    {
      "id": "seo_intermediate_风险控制_080",
      "originalId": 80,
      "category": "风险控制",
      "categoryKey": "风险控制",
      "type": "single",
      "question": "如何评估黑帽项目的风险等级？",
      "options": [
        "技术难度+检测概率+惩罚严重度",
        "不评估",
        "都一样",
        "随机判断"
      ],
      "answer": "技术难度+检测概率+惩罚严重度",
      "explanation": "风险评估指导决策"
    },
    {
      "id": "seo_intermediate_风险控制_081",
      "originalId": 81,
      "category": "风险控制",
      "categoryKey": "风险控制",
      "type": "multiple",
      "question": "数据安全措施包括？（多选）",
      "options": [
        "加密存储",
        "访问控制",
        "备份恢复",
        "日志审计"
      ],
      "answer": [
        "加密存储",
        "访问控制",
        "备份恢复",
        "日志审计"
      ],
      "explanation": "数据安全是基础保障"
    },
    {
      "id": "seo_intermediate_风险控制_082",
      "originalId": 82,
      "category": "风险控制",
      "categoryKey": "风险控制",
      "type": "single",
      "question": "如何处理被举报的风险？",
      "options": [
        "快速响应+问题排查+合理解释",
        "不理会",
        "删除证据",
        "威胁举报者"
      ],
      "answer": "快速响应+问题排查+合理解释",
      "explanation": "正确处理降低损失"
    },
    {
      "id": "seo_intermediate_风险控制_083",
      "originalId": 83,
      "category": "风险控制",
      "categoryKey": "风险控制",
      "type": "single",
      "question": "灰帽SEO的界限在哪里？",
      "options": [
        "不明确违反指南但有风险",
        "完全合规",
        "明确违规",
        "没有界限"
      ],
      "answer": "不明确违反指南但有风险",
      "explanation": "灰帽处于黑白之间"
    },
    {
      "id": "seo_intermediate_风险控制_084",
      "originalId": 84,
      "category": "风险控制",
      "categoryKey": "风险控制",
      "type": "single",
      "question": "如何建立风险预警机制？",
      "options": [
        "数据监控+异常告警+应急预案",
        "事后处理",
        "不建立",
        "随机应对"
      ],
      "answer": "数据监控+异常告警+应急预案",
      "explanation": "预警机制减少损失"
    },
    {
      "id": "seo_intermediate_风险控制_085",
      "originalId": 85,
      "category": "风险控制",
      "categoryKey": "风险控制",
      "type": "multiple",
      "question": "项目风险分散策略包括？（多选）",
      "options": [
        "多域名",
        "多IP",
        "多策略",
        "多变现"
      ],
      "answer": [
        "多域名",
        "多IP",
        "多策略",
        "多变现"
      ],
      "explanation": "分散风险提高生存能力"
    },
    {
      "id": "seo_intermediate_风险控制_086",
      "originalId": 86,
      "category": "风险控制",
      "categoryKey": "风险控制",
      "type": "single",
      "question": "如何判断是否触发了搜索引擎惩罚？",
      "options": [
        "流量骤降+排名消失+收录减少",
        "流量增加",
        "排名稳定",
        "没有变化"
      ],
      "answer": "流量骤降+排名消失+收录减少",
      "explanation": "多个信号表明被惩罚"
    },
    {
      "id": "seo_intermediate_风险控制_087",
      "originalId": 87,
      "category": "风险控制",
      "categoryKey": "风险控制",
      "type": "single",
      "question": "DMCA投诉的应对策略是？",
      "options": [
        "核实内容+及时处理+防止再犯",
        "忽略投诉",
        "继续使用",
        "反投诉"
      ],
      "answer": "核实内容+及时处理+防止再犯",
      "explanation": "正确处理版权投诉"
    },
    {
      "id": "seo_intermediate_风险控制_088",
      "originalId": 88,
      "category": "风险控制",
      "categoryKey": "风险控制",
      "type": "single",
      "question": "如何评估合作方的可靠性？",
      "options": [
        "背景调查+试用期+分阶段合作",
        "完全信任",
        "不评估",
        "直接合作"
      ],
      "answer": "背景调查+试用期+分阶段合作",
      "explanation": "谨慎选择合作伙伴"
    },
    {
      "id": "seo_intermediate_风险控制_089",
      "originalId": 89,
      "category": "风险控制",
      "categoryKey": "风险控制",
      "type": "multiple",
      "question": "隐私合规要求包括？（多选）",
      "options": [
        "用户同意",
        "数据最小化",
        "安全保护",
        "透明公开"
      ],
      "answer": [
        "用户同意",
        "数据最小化",
        "安全保护",
        "透明公开"
      ],
      "explanation": "隐私合规避免法律风险"
    },
    {
      "id": "seo_intermediate_风险控制_090",
      "originalId": 90,
      "category": "风险控制",
      "categoryKey": "风险控制",
      "type": "single",
      "question": "如何应对搜索引擎的人工审核？",
      "options": [
        "内容优化+用户体验+合理解释",
        "贿赂审核",
        "威胁投诉",
        "放弃网站"
      ],
      "answer": "内容优化+用户体验+合理解释",
      "explanation": "正规应对人工审核"
    },
    {
      "id": "seo_intermediate_风险控制_091",
      "originalId": 91,
      "category": "风险控制",
      "categoryKey": "风险控制",
      "type": "single",
      "question": "黑帽SEO的道德边界是？",
      "options": [
        "不损害用户利益和体验",
        "没有边界",
        "只要赚钱",
        "都不道德"
      ],
      "answer": "不损害用户利益和体验",
      "explanation": "考虑道德因素长远发展"
    },
    {
      "id": "seo_intermediate_风险控制_092",
      "originalId": 92,
      "category": "风险控制",
      "categoryKey": "风险控制",
      "type": "single",
      "question": "如何处理内部泄密风险？",
      "options": [
        "权限管理+保密协议+技术防护",
        "完全公开",
        "不防范",
        "事后追责"
      ],
      "answer": "权限管理+保密协议+技术防护",
      "explanation": "内部安全同样重要"
    },
    {
      "id": "seo_intermediate_风险控制_093",
      "originalId": 93,
      "category": "风险控制",
      "categoryKey": "风险控制",
      "type": "multiple",
      "question": "应急响应流程包括？（多选）",
      "options": [
        "问题识别",
        "影响评估",
        "处置执行",
        "复盘总结"
      ],
      "answer": [
        "问题识别",
        "影响评估",
        "处置执行",
        "复盘总结"
      ],
      "explanation": "完整流程确保有效应对"
    },
    {
      "id": "seo_intermediate_风险控制_094",
      "originalId": 94,
      "category": "风险控制",
      "categoryKey": "风险控制",
      "type": "single",
      "question": "如何平衡风险和收益？",
      "options": [
        "量化评估+动态调整+底线思维",
        "只看收益",
        "忽略风险",
        "保守操作"
      ],
      "answer": "量化评估+动态调整+底线思维",
      "explanation": "平衡是长期发展的关键"
    },
    {
      "id": "seo_intermediate_风险控制_095",
      "originalId": 95,
      "category": "风险控制",
      "categoryKey": "风险控制",
      "type": "single",
      "question": "项目失败后的处理原则是？",
      "options": [
        "总结经验+止损退出+资源回收",
        "继续投入",
        "完全放弃",
        "转嫁损失"
      ],
      "answer": "总结经验+止损退出+资源回收",
      "explanation": "正确处理失败项目"
    },
    {
      "id": "seo_intermediate_风险控制_096",
      "originalId": 96,
      "category": "风险控制",
      "categoryKey": "风险控制",
      "type": "single",
      "question": "如何建立行业情报网络？",
      "options": [
        "社群交流+工具监控+信息整合",
        "闭门造车",
        "不交流",
        "只靠自己"
      ],
      "answer": "社群交流+工具监控+信息整合",
      "explanation": "情报网络提供决策支持"
    },
    {
      "id": "seo_intermediate_风险控制_097",
      "originalId": 97,
      "category": "风险控制",
      "categoryKey": "风险控制",
      "type": "multiple",
      "question": "合规运营的要点包括？（多选）",
      "options": [
        "了解规则",
        "技术合规",
        "内容合规",
        "财务合规"
      ],
      "answer": [
        "了解规则",
        "技术合规",
        "内容合规",
        "财务合规"
      ],
      "explanation": "全面合规降低风险"
    },
    {
      "id": "seo_intermediate_风险控制_098",
      "originalId": 98,
      "category": "风险控制",
      "categoryKey": "风险控制",
      "type": "single",
      "question": "如何应对行业监管加强？",
      "options": [
        "转型升级+合规改造+创新突破",
        "继续违规",
        "退出行业",
        "观望等待"
      ],
      "answer": "转型升级+合规改造+创新突破",
      "explanation": "适应变化才能生存"
    },
    {
      "id": "seo_intermediate_风险控制_099",
      "originalId": 99,
      "category": "风险控制",
      "categoryKey": "风险控制",
      "type": "single",
      "question": "风险管理的核心原则是？",
      "options": [
        "预防为主+损失最小化+快速恢复",
        "不管风险",
        "风险最大化",
        "随机应对"
      ],
      "answer": "预防为主+损失最小化+快速恢复",
      "explanation": "风险管理保障项目成功"
    },
    {
      "id": "seo_intermediate_风险控制_100",
      "originalId": 100,
      "category": "风险控制",
      "categoryKey": "风险控制",
      "type": "single",
      "question": "中级SEO优化师的核心竞争力是？",
      "options": [
        "技术能力+项目经验+风险意识",
        "只靠技术",
        "只靠经验",
        "只靠关系"
      ],
      "answer": "技术能力+项目经验+风险意识",
      "explanation": "综合能力决定发展高度"
    }
  ]
}